skimage3d/__init__.py
skimage3d/py.typed
skimage3d-0.0.1.dist-info/METADATA
skimage3d-0.0.1.dist-info/WHEEL
skimage3d-0.0.1.dist-info/licenses/LICENSE
skimage3d-0.0.1.dist-info/RECORD
